pylunix_icon_kit/cli.py
pylunix_icon_kit/generator.py
pylunix_icon_kit-1.0.0.dist-info/licenses/LICENSE
pylunix_icon_kit-1.0.0.dist-info/METADATA
pylunix_icon_kit-1.0.0.dist-info/WHEEL
pylunix_icon_kit-1.0.0.dist-info/entry_points.txt
pylunix_icon_kit-1.0.0.dist-info/top_level.txt
pylunix_icon_kit-1.0.0.dist-info/RECORD
