Metadata-Version: 2.4
Name: pylunix_icon_kit
Version: 1.0.0
Summary: A PyLunix tool to generate Python QIcon modules from SVG themes
Author-email: Magicsoldier19 <magicsoldier19@gmail.com>
License: MIT
Project-URL: Homepage, https://github.com/JIA-WEI-LI/pylunix_icon_kit
Requires-Python: >=3.8
License-File: LICENSE
Requires-Dist: pyqt5
Provides-Extra: dev
Requires-Dist: twine>=6.1.0; extra == "dev"
Requires-Dist: build; extra == "dev"
Dynamic: license-file
